{
  "updatedAt": "05/05/2026, 18:00",
  "cards": {
    "sentimento": {
      "text1": "POLYMARKET (05/Mai noite, 18:00 BRT): LULA ESTÁVEL 36.50% (mantém o piso) × FLÁVIO LEVE CEDE 44.05% (↓0.20pp de 44.25%) com gap em leve compressão +7.55pp (vs +7.75pp ontem). STF IMPEACH DEVOLVE FORTE 12.00% (↓1.0pp continua queda de 13.00%) movimento mais relevante do dia mercado precifica institucionalidade firme. 2º LUGAR FLÁVIO DEVOLVE FORTE 62.50% (↓4.0pp leve cede consolidação de 66.50%) + CAMILO 2L DISPARA 5.75% (↑1.90pp de 3.85%) + ALCKMIN 2L DISPARA 2.20% (↑1.65pp de 0.55%) + HADDAD 2L 4.70% (↑1.05pp). 3º LUGAR REORGANIZAÇÃO: Zema mantém liderança 38.00%, Renan RECUPERA 36% (↑5pp de 31%), Caiado DEVOLVE 16.5% (↓2.5pp de 19%), Flávio 3L DEVOLVE 5.4% (↓4.65pp de 10.05%), Eduardo Leite DISPARA 3.0% (↑2.15pp de 0.85%). ZEMA presidencial DEVOLVE 4.65% (↓0.40pp reverte recuperação de ontem 5.05%). HADDAD presidencial recupera leve 3.15% (↑0.10pp). CAIADO 1.15% (↓0.10pp leve). CAMILO 3.55% (↓0.30pp leve). RENAN 5.45% (↓0.10pp leve estável). SENADO REORGANIZAÇÃO: PL 86.50% (↑0.50pp leve consolidação), União 5.30% (↑0.95pp recupera), MDB 4.90% (↑1.45pp recupera forte), Republicanos 2.35% (↑1.0pp DISPARA), Podemos 1.25% (↑0.70pp), PSB DEVOLVE 2.40% (↓0.85pp), PSD 5.40% (↓0.45pp leve). INFLAÇÃO: banda 5.00-5.49% consolida 38.40% (↑1.85pp), 6.00-6.49% DEVOLVE 16.95% (↓3.35pp corrige após dispara ontem), 7.00%+ DISPARA 11.80% (↑1.50pp). REAL TIME BIG DATA NACIONAL PUBLICADA 05/MAI: Lula 40% × Flávio 34% (1T sample 2.000, campo 02-04/Mai, BR-03627/2026), 2T Flávio 44% × Lula 43% empate técnico, 2T Caiado 42% × Lula 43% empate, 2T Zema × Lula empate técnico. Lula × Trump reunião quinta 07/Mai (D-launch) tensão e desconfiança. PF + PGR negociam só em conjunto delações INSS e Master.",
      "text2": "NOTÍCIAS-CHAVE (05/Mai): PESQUISA NACIONAL: 'Real Time Big Data: Lula supera Flávio na disputa pelo 1º turno' (CNN Brasil 05/Mai 10:01) Lula 40% × Flávio 34% sample 2.000 campo 02-04/Mai. 'Flávio tem 44%, e Lula 43% no 2º turno, aponta Real Time Big Data' (R7 05/Mai 10:31) empate técnico. 'Lula empata com Flávio, Caiado e Zema no 2º turno, diz pesquisa' (Estadão 05/Mai 11:48) cenários competitivos. 'Real Time: Com 40% a 34%, Lula lidera 1º turno mas vantagem sobre Flávio encolhe' (InfoMoney 05/Mai 11:43). 'Eleições 2026: Flávio Bolsonaro lidera cenário de 2º turno contra Lula' (R7 05/Mai 22:32). 'Pesquisas eleitorais: Quem está à frente na disputa para Presidência?' (BBC 05/Mai 08:08) agregador. 'Lula lidera 1º turno, seguido por Flávio Bolsonaro, aponta nova pesquisa' (Estado de Minas 05/Mai 17:07). DINÂMICA LULA-TRUMP: 'Casa Branca confirma encontro entre Lula e Trump na quinta-feira' (MSN 06/Mai 00:04) reunião 07/Mai dia D launch AFOS. 'Encontro de Lula e Trump é cercado de tensão e desconfiança' (Estado de Minas 05/Mai 13:18). 'Alckmin diz que Lula quer assinar acordo de combate ao crime organizado em reunião com Trump' (Folha 05/Mai 18:38). 'Lula buscará reduzir ruídos com Trump e minimizar factoides' (CNN Brasil 06/Mai 00:27). 'Lula terá carta na manga com Trump após aprovação do PL dos Minerais Críticos' (SBT News 05/Mai 17:54). 'Pix, minerais críticos e tarifas: agenda econômica em pauta' (Terra 05/Mai 09:01). MAS: 'Desaprovação de Lula sobe a 52% ampliando pressão após derrotas' (InfoMoney 05/Mai 14:09). 'Governo se divide sobre reação de Trump em visita de Lula' (CNN Brasil 05/Mai 13:23). DINÂMICA OPOSIÇÃO: 'Tarcísio lança presidente da Alesp ao Senado e critica Haddad' (Folha 05/Mai 18:21) articulação SP intensifica. 'Flávio faz bate e volta aos EUA às vésperas da reunião entre Lula e Trump' (Poder360 05/Mai 17:04) Flávio sinaliza presença internacional. 'Temor de vitória de Flávio Bolsonaro leva aprovados em concursos a pressionar por nomeações' (Folha 05/Mai 09:00). 'Flávio avança e Nordeste já não é território garantido para Lula' (Gazeta do Povo 05/Mai 00:47 mantida). 'Pesquisas indicam incertezas para PT e PL e vantagem de aliados de Flávio em maiores palanques' (Folha 05/Mai 02:00 mantida). 'Extrema direita tenta usar pesquisa para desgastar imagem de Lula' (Brasil de Fato 05/Mai 23:07). MASTER/INSS: 'PF e PGR decidem negociar só em conjunto delações de INSS e Master' (SBT News 05/Mai 16:26) coordenação institucional. 'CPI do Crime Organizado entra na reta final com foco no caso Master' (Times Brasil/CNBC 05/Mai 05:15). 'Senador denuncia armação do PT em cobrança pela CPI do Banco Master' (Portal 96FM 05/Mai 21:51). TSE: 'TSE lança mascote para as eleições de 2026' (Brasil 247 05/Mai 14:31, mantido).",
      "text3": "DADOS DO DIA (05/Mai 18:00): POLYMARKET PRESIDENCIAL: Lula 36.50% (estável mantém piso) × Flávio 44.05% (↓0.20pp leve cede de 44.25%), gap +7.55pp Flávio (leve compressão vs +7.75pp ontem). Renan 5.45% (↓0.10pp leve estável). ZEMA DEVOLVE 4.65% (↓0.40pp reverte recuperação ontem de 5.05%, volta abaixo dos 5%). Camilo 3.55% (↓0.30pp leve). Haddad recupera leve 3.15% (↑0.10pp de 3.05%). Caiado 1.15% (↓0.10pp leve). Bolsonaro 0.75% (estável). Alckmin 0.45% (estável). Michelle 0.35%. Eduardo Bolsonaro 0.25%. Tarcísio, E. Leite, Massa Ratinho, Aldo Rebelo todos 0.15% estáveis. 2º LUGAR REORGANIZAÇÃO: Flávio 62.50% (↓4.0pp DEVOLVE FORTE de 66.50%), Lula 19.50% (estável), Camilo 5.75% (↑1.90pp DISPARA de 3.85%), Renan 4.85% (estável), Haddad 4.70% (↑1.05pp de 3.65%), Alckmin 2.20% (↑1.65pp DISPARA de 0.55%), Zema 2.00% (↓0.35pp leve), Caiado 0.55% (estável), Bolsonaro 0.25%, Ratinho 0.25%. 3º LUGAR REORGANIZAÇÃO REVERSA: Zema 38.00% (estável mantém liderança), Renan 36.00% (↑5pp RECUPERA de 31%), Caiado 16.50% (↓2.5pp DEVOLVE de 19%), Flávio 5.40% (↓4.65pp DEVOLVE forte de 10.05%), Haddad 4.15% (estável), Eduardo Leite 3.00% (↑2.15pp DISPARA de 0.85%), Camilo 1.05% (↑0.35pp leve), Tarcísio 0.65% (↑0.40pp leve), Bolsonaro 0.50%, Eduardo Bolsonaro 0.25%, Lula 0.25%, Michelle 0.25%, Alckmin 0.25%, Aldo 0.15%. STF IMPEACH 12.00% (↓1.0pp DEVOLVE FORTE de 13.00%) institucionalidade firme mercado precifica baixa probabilidade impeachment até 2027. SENADO REORGANIZAÇÃO: PL 86.50% (↑0.50pp leve consolidação), PSD 5.40% (↓0.45pp leve), União 5.30% (↑0.95pp recupera de 4.35%), MDB 4.90% (↑1.45pp recupera forte de 3.45%), NOVO 3.75% (↓0.10pp leve), PSB 2.40% (↓0.85pp DEVOLVE de 3.25%), Republicanos 2.35% (↑1.0pp DISPARA de 1.35%), PT 2.25% (estável), Podemos 1.25% (↑0.70pp DISPARA), PSDB 0.55% (↓0.30pp leve), PP 0.25%, PDT 0.15%. INFLAÇÃO 2026: 5.00-5.49% consolida 38.40% (↑1.85pp), 4.50-4.99% mantém 22.00%, 6.00-6.49% DEVOLVE 16.95% (↓3.35pp corrige após dispara ontem), 3.00-3.49% 13.50% (↑0.20pp leve), 6.50-6.99% 13.20% (↑0.60pp leve), 7.00%+ DISPARA 11.80% (↑1.50pp), 5.50-5.99% 11.60% (↓1.75pp), 4.00-4.49% 8.70% (↓0.95pp leve), 3.50-3.99% 2.00% (estável), <3.00% 0.60% (↑0.35pp leve).",
      "direita": "POLYMARKET (05/Mai noite): Flávio leve cede 44.05% (↓0.20pp de 44.25% mantém liderança forte) × Lula estável 36.50%, gap em leve compressão +7.55pp (vs +7.75pp ontem). 2º lugar 62.50% (↓4.0pp DEVOLVE FORTE de 66.50% cede consolidação significativamente). 3º Flávio DEVOLVE 5.40% (↓4.65pp de 10.05% recupera realismo). 'Real Time Big Data: 1T Lula 40% × Flávio 34%' (CNN Brasil 05/Mai 10:01 sample 2.000 campo 02-04/Mai BR-03627/2026). 'Flávio tem 44% e Lula 43% no 2º turno, aponta Real Time Big Data' (R7 05/Mai 10:31) empate técnico. 'Eleições 2026: Flávio Bolsonaro lidera cenário de 2º turno contra Lula' (R7 05/Mai 22:32). 'Tarcísio lança presidente da Alesp ao Senado e critica Haddad' (Folha 05/Mai 18:21) articulação SP intensifica. 'Flávio faz bate e volta aos EUA às vésperas da reunião entre Lula e Trump' (Poder360 05/Mai 17:04) presença internacional. 'Temor de vitória de Flávio Bolsonaro leva aprovados em concursos a pressionar por nomeações' (Folha 05/Mai 09:00) sinal mercado de trabalho precifica vitória. 'Pesquisas indicam vantagem aliados Flávio maiores palanques' (Folha 05/Mai mantida). PL Senado consolida 86.50% (↑0.50pp leve). Republicanos DISPARA Senado 2.35% (↑1.0pp). MDB recupera forte Senado 4.90% (↑1.45pp). MAS: STF impeach DEVOLVE FORTE 12.00% (↓1.0pp) institucionalidade firme reduz espaço narrativa anti-STF. 'Flávio avança e Nordeste já não é território garantido para Lula' (Gazeta do Povo 05/Mai mantida). 'Extrema direita tenta usar pesquisa para desgastar imagem de Lula' (Brasil de Fato 05/Mai 23:07) crítica simétrica. Caiado 3L DEVOLVE 16.5% (↓2.5pp). Senado: PSD leve cede 5.40%, PSB DEVOLVE 2.40%.",
      "esquerda": "POLYMARKET (05/Mai noite): Lula estável 36.50% (mantém piso) gap leve compressão +7.55pp Flávio (vs +7.75pp ontem). 2º lugar Lula 19.50% (estável). 'Real Time Big Data: Lula supera Flávio na disputa pelo 1º turno' (CNN Brasil 05/Mai 10:01) Lula 40% × Flávio 34% (sample 2.000 campo 02-04/Mai). 'Lula empata com Flávio, Caiado e Zema no 2º turno, diz pesquisa' (Estadão 05/Mai 11:48) viabilidade institucional preservada nos 3 cenários competitivos. 'A popularidade de Lula a 5 meses da eleição, segundo nova pesquisa' (CartaCapital 05/Mai 12:14). 'Casa Branca confirma encontro entre Lula e Trump na quinta-feira' (MSN 06/Mai 00:04) reunião 07/Mai (DIA D LANÇAMENTO AFOS). 'Lula terá carta na manga com Trump após aprovação do PL dos Minerais Críticos' (SBT News 05/Mai 17:54). 'Alckmin diz que Lula quer assinar acordo de combate ao crime organizado em reunião com Trump' (Folha 05/Mai 18:38). 'Lula buscará reduzir ruídos com Trump e minimizar factoides' (CNN Brasil 06/Mai 00:27). 'Pix, minerais críticos e tarifas: agenda econômica em pauta' (Terra 05/Mai 09:01). 'Brasil e EUA negociam acordo de combate ao narcotráfico antes da reunião' (O Globo 05/Mai 15:43). 'Na véspera de encontro de Lula e Trump, Câmara vota política para minerais críticos' (InfoMoney 05/Mai 15:02) base parlamentar entrega vitória. STF impeach DEVOLVE FORTE 12.00% (↓1.0pp) preserva institucionalidade. Haddad recupera leve presidencial 3.15% (↑0.10pp). Camilo 2L DISPARA 5.75% (↑1.90pp). Haddad 2L recupera 4.70% (↑1.05pp). MAS: 'Desaprovação de Lula sobe a 52% ampliando pressão após derrotas' (InfoMoney 05/Mai 14:09). 'Governo se divide sobre reação de Trump em visita de Lula' (CNN Brasil 05/Mai 13:23). 'Encontro de Lula e Trump é cercado de tensão e desconfiança' (Estado de Minas 05/Mai 13:18). 'Senador denuncia armação do PT em cobrança pela CPI do Banco Master' (Portal 96FM 05/Mai 21:51) ataque CPI. 'CPI do Crime Organizado entra na reta final com foco no caso Master' (Times Brasil/CNBC 05/Mai). PT Senado 2.25% (estável).",
      "terceiraVia": "POLYMARKET (05/Mai noite): 3º LUGAR REORGANIZAÇÃO REVERSA da reversa: Zema 38.00% (estável mantém liderança), Renan RECUPERA 36% (↑5pp de 31%), reduz gap competidor 3ª via emerge novamente. Caiado DEVOLVE 16.5% (↓2.5pp de 19%) corrige movimento extremo de ontem. Flávio 3L DEVOLVE 5.4% (↓4.65pp de 10.05%). Eduardo Leite 3L DISPARA 3.0% (↑2.15pp de 0.85%) competidor liberal centro-direita recupera força. PRESIDENCIAL: ZEMA DEVOLVE presidencial 4.65% (↓0.40pp reverte recuperação ontem 5.05%, volta abaixo dos 5%). Renan 5.45% (↓0.10pp leve estável). Caiado 1.15% (↓0.10pp leve). Camilo 3.55% (↓0.30pp leve). Haddad 3.15% (↑0.10pp leve). 'Real Time Big Data: 1T Caiado 5%, Zema 4%, Renan 3%, Augusto Cury 1%' (CNN 05/Mai 10:01 sample 2.000) — Renan abaixo dos 5% confirma fragmentação 3ª via. 'Augusto Cury (Avante) 1%' (Real Time Big Data) novo entrante 3ª via simbólica. 'Lula empata com Flávio, Caiado e Zema no 2º turno' (Estadão 05/Mai 11:48) Caiado e Zema viáveis 2T. 'Eleições 2026: o que são agregadores de pesquisas eleitorais' (BBC 05/Mai 10:58) ciclo intensifica acompanhamento. STF impeach DEVOLVE FORTE 12.00% (↓1.0pp) reduz espaço narrativa anti-establishment Zema. 'Tarcísio lança presidente da Alesp ao Senado' (Folha 05/Mai 18:21) articulação SP. PSDB Senado leve cede 0.55% (↓0.30pp). Republicanos Senado DISPARA 2.35% (↑1.0pp) coalizão direita estadual emerge. Podemos Senado DISPARA 1.25% (↑0.70pp). MDB Senado recupera forte 4.90% (↑1.45pp) coalizão centrão recompõe. NOVO Senado leve cede 3.75% (↓0.10pp). Inflação banda 6.00-6.49% DEVOLVE 16.95% (↓3.35pp corrige após dispara ontem) reduz oxigênio discurso fiscal Zema momentaneamente.",
      "polymarket": "POLYMARKET (05/Mai 18:00): Lula 36.50% (estável piso) × Flávio 44.05% (↓0.20pp leve cede de 44.25%), gap +7.55pp Flávio (leve compressão vs +7.75pp ontem). Renan 5.45% (↓0.10pp leve estável). ZEMA DEVOLVE 4.65% (↓0.40pp reverte recuperação ontem). Camilo 3.55% (↓0.30pp leve). Haddad recupera leve 3.15% (↑0.10pp). Caiado 1.15% (↓0.10pp leve). Bolsonaro 0.75% (estável). Alckmin 0.45% (estável). Michelle 0.35%. Eduardo Bolsonaro 0.25%. Tarcísio, Eduardo Leite, Massa Ratinho, Aldo Rebelo 0.15% estáveis. 2º LUGAR: Flávio 62.50% (↓4.0pp DEVOLVE FORTE), Lula 19.50% (estável), Camilo 5.75% (↑1.90pp DISPARA), Renan 4.85% (estável), Haddad 4.70% (↑1.05pp), Alckmin 2.20% (↑1.65pp DISPARA), Zema 2.00% (↓0.35pp leve), Caiado 0.55% (estável), Bolsonaro 0.25%, Ratinho 0.25%, Eduardo Bolsonaro 0.15%, Tarcísio 0.15%, Michelle 0.15%, Eduardo Leite 0.15%, Aldo 0.15%. 3º LUGAR REORGANIZAÇÃO REVERSA: Zema 38.00% (estável mantém liderança), Renan 36.00% (↑5pp RECUPERA), Caiado 16.50% (↓2.5pp DEVOLVE), Flávio 5.40% (↓4.65pp DEVOLVE), Haddad 4.15% (estável), Eduardo Leite 3.00% (↑2.15pp DISPARA), Camilo 1.05% (↑0.35pp), Tarcísio 0.65% (↑0.40pp), Bolsonaro 0.50%, Eduardo Bolsonaro 0.25%, Lula 0.25%, Michelle 0.25%, Alckmin 0.25%, Aldo 0.15%. STF IMPEACH 12.00% (↓1.0pp DEVOLVE FORTE de 13.00%) institucionalidade firme. SENADO REORGANIZAÇÃO: PL 86.50% (↑0.50pp leve), PSD 5.40% (↓0.45pp leve), União 5.30% (↑0.95pp recupera), MDB 4.90% (↑1.45pp recupera forte), NOVO 3.75% (↓0.10pp leve), PSB 2.40% (↓0.85pp DEVOLVE), Republicanos 2.35% (↑1.0pp DISPARA), PT 2.25% (estável), Podemos 1.25% (↑0.70pp DISPARA), PSDB 0.55% (↓0.30pp leve), PP 0.25%, PDT 0.15%. INFLAÇÃO: 5.00-5.49% consolida 38.40% (↑1.85pp), 4.50-4.99% mantém 22.00%, 6.00-6.49% DEVOLVE 16.95% (↓3.35pp corrige), 3.00-3.49% 13.50% (↑0.20pp), 6.50-6.99% 13.20% (↑0.60pp leve), 7.00%+ DISPARA 11.80% (↑1.50pp), 5.50-5.99% 11.60% (↓1.75pp), 4.00-4.49% 8.70%, 3.50-3.99% 2.00%, <3.00% 0.60% (↑0.35pp leve). NOTÍCIAS 05/Mai: Real Time Big Data 1T Lula 40% × Flávio 34% + 2T Flávio 44% × Lula 43% empate + 2T Caiado 42% × Lula 43% + 2T Zema empate técnico (sample 2.000 campo 02-04/Mai BR-03627/2026) + Lula × Trump reunião 07/Mai (D launch) tensão e desconfiança + Tarcísio crítica Haddad lança presidente Alesp Senado + Flávio bate-volta EUA véspera Lula-Trump + Desaprovação Lula sobe 52% (InfoMoney) + PF + PGR negociam só conjunto delações INSS + Master + CPI Crime Organizado reta final foco Master + TSE mascote Pilili."
    },
    "inss": {
      "text1": "INSS+MASTER (05/Mai): 'PF e PGR decidem negociar só em conjunto delações de INSS e Master' (SBT News 05/Mai 16:26) coordenação institucional escalada cooperação investigativa. 'CPI do Crime Organizado entra na reta final com foco no caso Master' (Times Brasil/CNBC 05/Mai 05:15). 'Senador denuncia armação do PT em cobrança pela CPI do Banco Master' (Portal 96FM 05/Mai 21:51) ataque político PT vs Senadores. Mantidos: 'Dados do Master recebidos pela CPI do INSS chegam a 30 GB de material' (CNN Brasil 04/Mai mantida); 'Celulares de Vorcaro serão enviados a EUA e Israel' (SBT News 04/Mai mantida); 'PF faz força-tarefa para fechar lista de autoridades com foro privilegiado no caso Master' (Brasil 247 04/Mai mantida); 'VORCARO tinha apoio dos mais altos escalões da República, diz Mendonça' (Metrópoles 02/Mai mantida); 'Costa Neto antecipou acordo entre Flávio Bolsonaro e Alcolumbre para barrar CPI do Master' (Revista Fórum 02/Mai mantida); 'PT deveria ter assinado CPI Banco Master, diz Edinho Silva' (O Antagonista 02/Mai mantida); 'PF analisa plea deal INSS sobre Master' (G1 30/Abr mantida); 'Caso Master: Ligação entre Gonet e Moraes é obstáculo' (CNN Brasil 03/Mai mantida).",
      "text2": "DINÂMICA INSTITUCIONAL (05/Mai): STF IMPEACH POLY DEVOLVE FORTE 12.00% (↓1.0pp continua queda de 13.00% movimento mais relevante do dia). Mercado precifica institucionalidade firme. 'Casa Branca confirma encontro entre Lula e Trump na quinta-feira' (MSN 06/Mai 00:04) reunião 07/Mai (D launch AFOS) cargo factual mais relevante do dia. 'Lula buscará reduzir ruídos com Trump e minimizar factoides' (CNN Brasil 06/Mai 00:27). 'Brasil e EUA negociam acordo de combate ao narcotráfico antes da reunião' (O Globo 05/Mai 15:43). 'Pix, minerais críticos e tarifas: agenda econômica em pauta' (Terra 05/Mai 09:01). 'Lula terá carta na manga com Trump após aprovação do PL dos Minerais Críticos' (SBT News 05/Mai 17:54). 'Na véspera de encontro de Lula e Trump, Câmara vota política para minerais críticos' (InfoMoney 05/Mai 15:02) base entrega vitória. 'Governo se divide sobre reação de Trump em visita de Lula' (CNN Brasil 05/Mai 13:23) tensão interna. 'Tarcísio lança presidente da Alesp ao Senado e critica Haddad' (Folha 05/Mai 18:21) articulação SP intensifica. 'Flávio faz bate e volta aos EUA às vésperas da reunião' (Poder360 05/Mai 17:04) presença internacional simbólica. 'PF e PGR decidem negociar só em conjunto delações INSS e Master' (SBT News 05/Mai 16:26) coordenação. 'CPI do Crime Organizado reta final foco Master' (Times Brasil 05/Mai). PL Senado consolida 86.50% (↑0.50pp leve). MDB recupera forte 4.90% (↑1.45pp). Republicanos Senado DISPARA 2.35% (↑1.0pp). Podemos DISPARA 1.25% (↑0.70pp). Mantidos: 'Tarcísio e Flávio reportados PG por crimes eleitorais' (Revista Fórum 02/Mai); 'STF avança casos impacto eleitoral esvazia TSE 2026' (Estadão 04/Mai mantida); 'Caso Master Gonet × Moraes obstáculo' (CNN 03/Mai mantida).",
      "text3": "STF IMPEACH 12.00% (05/Mai, ↓1.0pp DEVOLVE FORTE de 13.00%): trajetória 21 dias: 13.5 → 11 → 12 → 12.5 → 12.5 → 14 → 14 → 14 → 15.5 → 15 → 15 → 16 → 11 → 14 → 15 → 15.50 → 13.00 → 14.00 → 13.50 → 13.00 → 12.00% movimento mais relevante do dia. Razões precificadas: (1) 'Casa Branca confirma reunião Lula × Trump quinta-feira' (MSN 06/Mai) agenda institucional dominante reduz apetite anti-STF; (2) 'PF e PGR negociam só em conjunto delações INSS e Master' (SBT News 05/Mai) coordenação investigativa funcional reforça narrativa institucionalidade; (3) 'STF avança casos impacto eleitoral esvazia TSE 2026' (Estadão 04/Mai mantida) STF se firma como árbitro; (4) Real Time Big Data 1T Lula 40% lidera apesar de gap reduzir comparado AtlasIntel — sinaliza disputa competitiva mas dentro do quadro institucional; (5) 'Brasil e EUA negociam acordo combate narcotráfico' (O Globo 05/Mai) tema combate ao crime organizado domina narrativa institucional; (6) Inflação banda 6.00-6.49% DEVOLVE 16.95% (↓3.35pp) reduz tom catastrofista oposição. MAS: 'Tarcísio crítica Haddad lança presidente Alesp Senado' (Folha 05/Mai) articulação direita Senado mantém. 'Senador denuncia armação PT cobrança CPI Master' (Portal 96FM 05/Mai) ataque CPI Master mantém narrativa anti-instituições.",
      "text4": "CAMPO POLÍTICO (05/Mai noite): Lula estável Poly 36.50% × Flávio leve cede 44.05% (↓0.20pp), gap leve compressão +7.55pp Flávio. 2º lugar 62.50% (↓4.0pp DEVOLVE FORTE) × Lula 19.50% (estável). STF IMPEACH DEVOLVE FORTE 12.00% (↓1.0pp). ZEMA presidencial DEVOLVE 4.65% (↓0.40pp). 3º LUGAR Zema mantém liderança 38.00%, Renan RECUPERA 36% (↑5pp), Caiado DEVOLVE 16.5% (↓2.5pp), Flávio DEVOLVE 5.4% (↓4.65pp). Camilo presidencial 3.55% (↓0.30pp leve). Haddad recupera leve 3.15% (↑0.10pp). Camilo 2L DISPARA 5.75% (↑1.90pp). Haddad 2L recupera 4.70% (↑1.05pp). Alckmin 2L DISPARA 2.20% (↑1.65pp). Eduardo Leite 3L DISPARA 3.0% (↑2.15pp). SENADO REORGANIZAÇÃO: PL 86.50%, União 5.30% (↑0.95pp recupera), MDB 4.90% (↑1.45pp recupera forte), Republicanos 2.35% (↑1.0pp DISPARA), Podemos 1.25% (↑0.70pp), PSB DEVOLVE 2.40%. 'Real Time Big Data: Lula 40% × Flávio 34% (1T) + Flávio 44% × Lula 43% (2T)' (CNN, R7, Estadão 05/Mai sample 2.000). 'Casa Branca confirma reunião Lula × Trump quinta 07/Mai' (MSN 06/Mai). 'Tarcísio lança Alesp Senado crítica Haddad' (Folha 05/Mai). 'Flávio bate-volta EUA' (Poder360 05/Mai). 'Desaprovação Lula sobe 52%' (InfoMoney). PRÓXIMA LEVA: 06/Mai DIA-MEGA-BOMBA 7 pesquisas (DATATRENDS n=4000, Ideia/Canal Meio n=1500, VOX BRASIL n=1200, SETA n=1200, 100 Cidades n=1200, Inst Franca n=1067, NEOBE n=1008) ~11.175 entrevistados (registros TSE confirmados); 07/Mai J J COELHO n=1203 + reunião Lula × Trump; LAUNCH AFOS 12/Mai (terça-feira) + reunião Lula × Trump.",
      "impactoLula": "ESTÁVEL POLY (05/Mai noite): Lula estável Poly 36.50% (mantém piso) gap leve compressão +7.55pp Flávio (vs +7.75pp ontem). 2º lugar Lula 19.50% (estável). 'Real Time Big Data: Lula supera Flávio na disputa pelo 1º turno' (CNN Brasil 05/Mai 10:01) Lula 40% × Flávio 34% sample 2.000 campo 02-04/Mai BR-03627/2026. 'Lula empata com Flávio, Caiado e Zema no 2º turno' (Estadão 05/Mai 11:48) viabilidade institucional preservada nos 3 cenários. 'Casa Branca confirma encontro entre Lula e Trump na quinta-feira' (MSN 06/Mai 00:04) reunião 07/Mai (D launch AFOS) — momento institucional crítico. 'Lula terá carta na manga com Trump após aprovação do PL dos Minerais Críticos' (SBT News 05/Mai 17:54). 'Alckmin diz que Lula quer assinar acordo de combate ao crime organizado' (Folha 05/Mai 18:38). 'Brasil e EUA negociam acordo combate ao narcotráfico antes da reunião' (O Globo 05/Mai 15:43). 'Pix, minerais críticos e tarifas: agenda econômica em pauta' (Terra 05/Mai). 'Na véspera de encontro Lula × Trump, Câmara vota política minerais críticos' (InfoMoney 05/Mai). 'Lula buscará reduzir ruídos com Trump e minimizar factoides' (CNN Brasil 06/Mai 00:27). MAS: 'Desaprovação de Lula sobe a 52% ampliando pressão após derrotas' (InfoMoney 05/Mai 14:09) sinal pressão. 'Governo se divide sobre reação de Trump em visita de Lula' (CNN Brasil 05/Mai 13:23) tensão interna. 'Encontro Lula × Trump cercado de tensão e desconfiança' (Estado de Minas 05/Mai 13:18). 'Senador denuncia armação PT cobrança CPI Master' (Portal 96FM 05/Mai). 'Temor de vitória de Flávio Bolsonaro leva aprovados em concursos a pressionar por nomeações' (Folha 05/Mai 09:00) servidores antecipam cenário Flávio. 'Pesquisas indicam vantagem aliados Flávio maiores palanques' (Folha 05/Mai mantida). PT Senado 2.25% (estável). Aprovação 46.6-46.8% mantida pré-Real Time detalhes secundários.",
      "impactoGestao": "DINÂMICA JUDICIAL (05/Mai): STF IMPEACH POLY DEVOLVE FORTE 12.00% (↓1.0pp continua queda de 13.00% movimento mais relevante do dia institucionalidade firme). 'PF e PGR decidem negociar só em conjunto delações de INSS e Master' (SBT News 05/Mai 16:26) coordenação institucional. 'CPI do Crime Organizado entra na reta final com foco no caso Master' (Times Brasil/CNBC 05/Mai 05:15). 'Senador denuncia armação PT cobrança CPI Master' (Portal 96FM 05/Mai 21:51) tensão política. 'Casa Branca confirma encontro Lula × Trump quinta-feira' (MSN 06/Mai 00:04). 'Lula buscará reduzir ruídos com Trump e minimizar factoides' (CNN Brasil 06/Mai 00:27). 'Brasil e EUA negociam acordo combate ao narcotráfico' (O Globo 05/Mai 15:43). 'Tarcísio lança presidente Alesp Senado crítica Haddad' (Folha 05/Mai 18:21). 'Flávio bate-volta EUA véspera reunião Lula × Trump' (Poder360 05/Mai 17:04). 'Encontro Lula × Trump cercado de tensão e desconfiança' (Estado de Minas 05/Mai). 'Governo se divide sobre reação de Trump em visita de Lula' (CNN Brasil 05/Mai 13:23). Mantidos: 'Dados Master CPI INSS 30 GB' (CNN 04/Mai); 'Celulares Vorcaro EUA + Israel' (SBT News 04/Mai); 'PF força-tarefa foro privilegiado Master' (Brasil 247 04/Mai); 'STF avança casos impacto eleitoral esvazia TSE 2026' (Estadão 04/Mai); 'Tarcísio Flávio reportados PG' (Revista Fórum 02/Mai); 'Caso Master Gonet × Moraes obstáculo' (CNN 03/Mai); 'Vorcaro mais altos escalões República Mendonça' (Metrópoles); 'Costa Neto acordo Flávio × Alcolumbre' (Revista Fórum 02/Mai); 'Alcolumbre enterra CPI Master' (Folha 30/Abr).",
      "conclusao": "05/Mai NOITE 18:00h: (1) LULA ESTÁVEL Poly 36.50% (mantém piso) × Flávio leve cede 44.05% (↓0.20pp), gap leve compressão +7.55pp Flávio (vs +7.75pp ontem); (2) STF IMPEACH DEVOLVE FORTE 12.00% (↓1.0pp continua queda de 13.00% movimento mais relevante do dia); (3) 2º lugar Flávio DEVOLVE FORTE 62.50% (↓4.0pp de 66.50%) × Lula 19.50% estável; (4) Camilo 2L DISPARA 5.75% (↑1.90pp), Haddad 2L recupera 4.70% (↑1.05pp), Alckmin 2L DISPARA 2.20% (↑1.65pp); (5) 3º LUGAR REORGANIZAÇÃO REVERSA: Zema 38% mantém liderança, Renan RECUPERA 36% (↑5pp), Caiado DEVOLVE 16.5% (↓2.5pp), Flávio DEVOLVE 5.4% (↓4.65pp), Eduardo Leite DISPARA 3.0% (↑2.15pp); (6) ZEMA presidencial DEVOLVE 4.65% (↓0.40pp reverte recuperação ontem); (7) 'Real Time Big Data: 1T Lula 40% × Flávio 34% sample 2.000 campo 02-04/Mai BR-03627/2026' (CNN Brasil 05/Mai 10:01); (8) '2T Flávio 44% × Lula 43% empate técnico' (R7 05/Mai 10:31); (9) '2T Caiado 42% × Lula 43% empate' (Estadão 05/Mai 11:48); (10) 'Casa Branca confirma encontro Lula × Trump quinta-feira 07/Mai' (MSN 06/Mai 00:04 dia D LANÇAMENTO AFOS); (11) 'Lula terá carta na manga com Trump após aprovação do PL dos Minerais Críticos' (SBT News 05/Mai); (12) 'Brasil e EUA negociam acordo combate ao narcotráfico antes da reunião' (O Globo 05/Mai); (13) 'Tarcísio lança presidente da Alesp ao Senado e critica Haddad' (Folha 05/Mai 18:21); (14) 'Flávio faz bate e volta aos EUA às vésperas da reunião' (Poder360 05/Mai 17:04); (15) 'Desaprovação de Lula sobe a 52% ampliando pressão após derrotas' (InfoMoney 05/Mai 14:09); (16) 'Temor de vitória de Flávio Bolsonaro leva aprovados em concursos a pressionar por nomeações' (Folha 05/Mai 09:00); (17) 'Encontro de Lula e Trump cercado de tensão e desconfiança' (Estado de Minas 05/Mai); (18) 'Governo se divide sobre reação de Trump em visita de Lula' (CNN Brasil 05/Mai); (19) 'Augusto Cury (Avante) 1% no Real Time Big Data' (CNN 05/Mai) novo entrante 3ª via; (20) SENADO REORGANIZAÇÃO: PL 86.50% (↑0.50pp leve), União 5.30% recupera (↑0.95pp), MDB 4.90% recupera forte (↑1.45pp), Republicanos 2.35% DISPARA (↑1.0pp), Podemos 1.25% DISPARA (↑0.70pp), PSB DEVOLVE 2.40% (↓0.85pp); (21) INFLAÇÃO: banda 5.00-5.49% consolida 38.40% (↑1.85pp), 6.00-6.49% DEVOLVE 16.95% (↓3.35pp corrige), 7.00%+ DISPARA 11.80% (↑1.50pp); (22) 'PF e PGR decidem negociar só em conjunto delações de INSS e Master' (SBT News 05/Mai 16:26); (23) 'CPI Crime Organizado reta final foco Master' (Times Brasil 05/Mai); (24) 'Senador denuncia armação PT cobrança CPI Master' (Portal 96FM 05/Mai); (25) PRÓXIMA LEVA confirmada TSE: 06/Mai DIA-MEGA-BOMBA 7 pesquisas ~11.175 entrevistados, 07/Mai (J J COELHO + Lula × Trump); LAUNCH AFOS 12/Mai LAUNCH J J COELHO + reunião Lula × Trump."
    },
    "bancoMaster": {
      "text1": "MASTER (05/Mai): 'PF e PGR decidem negociar só em conjunto delações de INSS e Master' (SBT News 05/Mai 16:26) coordenação institucional escalada cooperação investigativa. 'CPI do Crime Organizado entra na reta final com foco no caso Master' (Times Brasil/CNBC 05/Mai 05:15) cerco institucional avança. 'Senador denuncia armação do PT em cobrança pela CPI do Banco Master' (Portal 96FM 05/Mai 21:51) ataque político PT vs Senadores. Mantidos: 'Dados do Master recebidos pela CPI do INSS chegam a 30 GB de material' (CNN Brasil 04/Mai mantida); 'Celulares de Vorcaro serão enviados a EUA e Israel' (SBT News 04/Mai mantida); 'PF faz força-tarefa para fechar lista de autoridades com foro privilegiado no caso Master' (Brasil 247 04/Mai mantida); 'VORCARO tinha apoio dos mais altos escalões da República, diz Mendonça' (Metrópoles 02/Mai mantida); 'Gleisi acusa Nikolas Ferreira de usar jatinho de Vorcaro' (Gazeta do Povo 02/Mai mantida); 'Costa Neto antecipou acordo entre Flávio Bolsonaro e Alcolumbre para barrar CPI do Master' (Revista Fórum 02/Mai mantida); 'PT deveria ter assinado CPI Banco Master, diz Edinho Silva' (O Antagonista 02/Mai mantida); 'PF analisa plea deal INSS sobre Master' (G1 30/Abr mantida); 'Caso Master: Ligação entre Gonet e Moraes é obstáculo' (CNN Brasil 03/Mai mantida).",
      "text2": "DINÂMICA INSTITUCIONAL (05/Mai): STF impeach Poly DEVOLVE FORTE 12.00% (↓1.0pp continua queda movimento mais relevante do dia). 'Casa Branca confirma encontro Lula × Trump quinta-feira' (MSN 06/Mai 00:04) reunião 07/Mai (Casa Branca confirmou) evento institucional dominante; launch AFOS reagendado para 12/Mai (terça-feira). 'Brasil e EUA negociam acordo de combate ao narcotráfico' (O Globo 05/Mai 15:43). 'Lula buscará reduzir ruídos com Trump' (CNN Brasil 06/Mai). 'Tarcísio lança presidente da Alesp ao Senado e critica Haddad' (Folha 05/Mai 18:21) articulação SP. 'Flávio bate-volta EUA véspera reunião' (Poder360 05/Mai). PL Senado consolida 86.50% (↑0.50pp leve). MDB recupera forte Senado 4.90% (↑1.45pp). Republicanos Senado DISPARA 2.35% (↑1.0pp). Podemos Senado DISPARA 1.25% (↑0.70pp). 'PF e PGR decidem negociar só em conjunto delações INSS e Master' (SBT News 05/Mai). 'CPI Crime Organizado reta final foco Master' (Times Brasil 05/Mai). Mantidos: 'Tarcísio e Flávio reportados PG por crimes eleitorais' (Revista Fórum 02/Mai); 'STF avança casos impacto eleitoral esvazia TSE 2026' (Estadão 04/Mai mantida); 'Caso Master Gonet × Moraes obstáculo' (CNN 03/Mai mantida); 'Alcolumbre enterra CPI Master' (Folha 30/Abr mantida).",
      "text3": "IMPACTO ELEITORAL (05/Mai noite): Lula estável Poly 36.50% × Flávio leve cede 44.05% (↓0.20pp), gap leve compressão +7.55pp Flávio (vs +7.75pp ontem). 2º lugar 62.50% (↓4.0pp DEVOLVE FORTE) × Lula 19.50% (estável). STF impeach DEVOLVE FORTE 12.00% (↓1.0pp). ZEMA DEVOLVE presidencial 4.65% (↓0.40pp reverte recuperação ontem). 3º LUGAR Zema 38% mantém liderança, Renan RECUPERA 36% (↑5pp), Caiado DEVOLVE 16.5%, Flávio DEVOLVE 5.4%, Eduardo Leite DISPARA 3.0%. Camilo presidencial 3.55% (↓0.30pp leve) > Haddad 3.15% (↑0.10pp leve). Camilo 2L DISPARA 5.75% (↑1.90pp). Haddad 2L recupera 4.70% (↑1.05pp). Alckmin 2L DISPARA 2.20% (↑1.65pp). SENADO: PL 86.50%, União 5.30% recupera, MDB 4.90% recupera forte, Republicanos 2.35% DISPARA, Podemos 1.25% DISPARA, PSB DEVOLVE 2.40%. Inflação banda 5.00-5.49% consolida 38.40% (↑1.85pp), 6.00-6.49% DEVOLVE 16.95% (↓3.35pp), 7.00%+ DISPARA 11.80% (↑1.50pp). 'Real Time Big Data 1T Lula 40% × Flávio 34% + 2T Flávio 44% × Lula 43% empate' (CNN, R7, Estadão 05/Mai sample 2.000). 'Casa Branca confirma reunião Lula × Trump quinta-feira' (MSN 06/Mai). 'Tarcísio lança Alesp Senado crítica Haddad' (Folha 05/Mai). 'Flávio bate-volta EUA' (Poder360 05/Mai). 'Desaprovação Lula sobe 52%' (InfoMoney 05/Mai). 'PF e PGR negociam só conjunto delações INSS + Master' (SBT News 05/Mai). 'CPI Crime Organizado reta final foco Master' (Times Brasil 05/Mai).",
      "conclusao": "Master 05/Mai 18:00h: (1) 'PF e PGR decidem negociar só em conjunto delações de INSS e Master' (SBT News 05/Mai 16:26); (2) 'CPI do Crime Organizado entra na reta final com foco no caso Master' (Times Brasil/CNBC 05/Mai 05:15); (3) 'Senador denuncia armação do PT em cobrança pela CPI do Banco Master' (Portal 96FM 05/Mai 21:51); (4) STF IMPEACH POLY DEVOLVE FORTE 12.00% (↓1.0pp continua queda de 13.00% movimento mais relevante do dia); (5) 'Casa Branca confirma encontro Lula × Trump quinta-feira 07/Mai' (MSN 06/Mai 00:04 dia D LANÇAMENTO AFOS); (6) Lula estável Poly 36.50% × Flávio leve cede 44.05% (↓0.20pp); (7) gap leve compressão +7.55pp Flávio (vs +7.75pp ontem); (8) 'Real Time Big Data 1T Lula 40% × Flávio 34%' (CNN Brasil 05/Mai 10:01 sample 2.000 campo 02-04/Mai BR-03627/2026); (9) '2T Flávio 44% × Lula 43% empate' (R7 05/Mai 10:31); (10) '2T Caiado 42% × Lula 43% empate' (Estadão 05/Mai 11:48); (11) 'Lula terá carta na manga com Trump após aprovação PL Minerais Críticos' (SBT News 05/Mai); (12) 'Brasil e EUA negociam acordo combate ao narcotráfico antes da reunião' (O Globo 05/Mai); (13) 'Tarcísio lança Alesp Senado crítica Haddad' (Folha 05/Mai 18:21); (14) 'Flávio bate-volta EUA véspera Lula × Trump' (Poder360 05/Mai 17:04); (15) 'Desaprovação Lula sobe 52%' (InfoMoney 05/Mai); (16) 'Temor vitória Flávio aprovados pressionam nomeações' (Folha 05/Mai); (17) Camilo 2L DISPARA 5.75% (↑1.90pp); (18) Eduardo Leite 3L DISPARA 3.0% (↑2.15pp); (19) Renan 3L RECUPERA 36% (↑5pp); (20) SENADO REORGANIZAÇÃO: PL 86.50% leve consolida, União 5.30% recupera, MDB 4.90% recupera forte, Republicanos 2.35% DISPARA, Podemos 1.25% DISPARA, PSB DEVOLVE 2.40%, PSD leve cede 5.40%; (21) INFLAÇÃO: banda 5.00-5.49% consolida 38.40% (↑1.85pp), 6.00-6.49% DEVOLVE 16.95% (↓3.35pp corrige), 7.00%+ DISPARA 11.80% (↑1.50pp); (22) 'Encontro Lula × Trump cercado de tensão e desconfiança' (Estado de Minas 05/Mai); (23) 'Governo se divide sobre reação de Trump' (CNN Brasil 05/Mai); (24) 'Pesquisas indicam vantagem aliados Flávio maiores palanques' (Folha 05/Mai mantida); (25) 'Augusto Cury (Avante) 1% novo entrante' (CNN Real Time Big Data 05/Mai)."
    },
    "stf": {
      "toffoli": "Mantido. STF IMPEACH POLY DEVOLVE FORTE 12.00% (↓1.0pp continua queda de 13.00% movimento mais relevante do dia institucionalidade firme). 'Casa Branca confirma encontro entre Lula e Trump na quinta-feira' (MSN 06/Mai 00:04) reunião 07/Mai institucional dominante. 'STF avança sobre casos com impacto eleitoral e pode esvaziar atuação do TSE em 2026' (Estadão 04/Mai mantida). Mantidos: 'STF Backlog 700 casos aguardando após Messias'; Alcolumbre enterra CPI Master (Folha 30/Abr); 'Caso Master: Ligação Gonet × Moraes obstáculo' (CNN 03/Mai mantida).",
      "moraes": "Mantido. 'Caso Master: Ligação entre Gonet e Moraes é obstáculo, dizem investigadores' (CNN Brasil 03/Mai mantida). 'PF e PGR decidem negociar só em conjunto delações de INSS e Master' (SBT News 05/Mai 16:26) coordenação institucional. 'Celulares de Vorcaro serão enviados a EUA e Israel' (SBT News 04/Mai mantida) cooperação internacional. 'PF faz força-tarefa para fechar lista de autoridades com foro privilegiado' (Brasil 247 04/Mai mantida). Mantidos: 'Lula aconselha Moraes Vorcaro biografia' (MSN); Família Moraes processa A. Vieira PCC; PF apura Moraes imóveis luxo. STF IMPEACH DEVOLVE FORTE 12.00% (↓1.0pp) ainda longe do pico 16% recente.",
      "gilmar": "Mantido. Gilmar duplo discurso mantido. STF IMPEACH 12.00% (↓1.0pp DEVOLVE FORTE). 'STF avança sobre casos impacto eleitoral pode esvaziar TSE 2026' (Estadão 04/Mai mantida). 'Caso Master Gonet × Moraes obstáculo' (CNN 03/Mai mantida). 'STF Backlog 700 casos' mantido. 'Casa Branca confirma reunião Lula × Trump quinta-feira' (MSN 06/Mai) agenda institucional dominante.",
      "dino": "Mantido. Ministros STF apostavam Messias aprovação confortável próximo a Dino mantido — apostas falharam: Messias REJEITADO 42×34. Alcolumbre 'novo STF será do vencedor' mantido pressão indireta sobre Dino. 'Nova indicação ao STF: Lula analisa opções após rejeição' (Diário do Estado 04/Mai mantida). 'Rejeição de Messias expõe grupos no STF' (Tribuna da Bahia 04/Mai mantida). 'Lula buscará reduzir ruídos com Trump' (CNN Brasil 06/Mai 00:27). 'Brasil e EUA negociam acordo combate ao narcotráfico' (O Globo 05/Mai). Religious Leaders Response mantido.",
      "nexo": "STF IMPEACH 12.00% (05/Mai noite, ↓1.0pp DEVOLVE FORTE de 13.00%): trajetória 21 dias: 13.5 → 11 → 12 → 12.5 → 12.5 → 14 → 14 → 14 → 15.5 → 15 → 15 → 16 → 11 → 14 → 15 → 15.50 → 13.00 → 14.00 → 13.50 → 13.00 → 12.00% movimento mais relevante do dia institucionalidade firme. Razões: (1) 'Casa Branca confirma reunião Lula × Trump quinta-feira' (MSN 06/Mai) agenda institucional dominante reduz apetite anti-STF; (2) 'PF e PGR decidem negociar só em conjunto delações INSS e Master' (SBT News 05/Mai) coordenação investigativa funcional reforça narrativa institucionalidade; (3) 'STF avança casos impacto eleitoral esvazia TSE 2026' (Estadão 04/Mai mantida) STF se firma como árbitro; (4) Real Time Big Data 1T Lula 40% lidera apesar gap reduzir vs AtlasIntel; (5) 'Brasil e EUA negociam acordo combate narcotráfico' (O Globo 05/Mai) tema dominante; (6) Inflação banda 6.00-6.49% DEVOLVE 16.95% (↓3.35pp corrige). MAS: 'Tarcísio crítica Haddad' (Folha 05/Mai). 'Senador denuncia armação PT cobrança CPI Master' (Portal 96FM 05/Mai) ataque CPI Master mantém narrativa anti-instituições.",
      "analise": "STF 05/Mai 18:00h, impeach DEVOLVE FORTE 12.00%: (1) STF impeach Poly 12.00% (↓1.0pp DEVOLVE FORTE de 13.00% movimento mais relevante do dia institucionalidade firme); (2) 'Casa Branca confirma encontro entre Lula e Trump na quinta-feira' (MSN 06/Mai 00:04) reunião 07/Mai (Casa Branca confirmou) evento institucional dominante; launch AFOS reagendado para 12/Mai (terça-feira); (3) 'PF e PGR decidem negociar só em conjunto delações de INSS e Master' (SBT News 05/Mai 16:26); (4) 'CPI do Crime Organizado entra na reta final com foco no caso Master' (Times Brasil/CNBC 05/Mai 05:15); (5) 'Senador denuncia armação do PT em cobrança pela CPI do Banco Master' (Portal 96FM 05/Mai 21:51); (6) 'STF avança sobre casos com impacto eleitoral e pode esvaziar atuação do TSE em 2026' (Estadão 04/Mai mantida); (7) 'Brasil e EUA negociam acordo de combate ao narcotráfico antes da reunião' (O Globo 05/Mai 15:43); (8) 'Lula terá carta na manga com Trump após aprovação do PL dos Minerais Críticos' (SBT News 05/Mai); (9) 'Lula buscará reduzir ruídos com Trump e minimizar factoides' (CNN Brasil 06/Mai 00:27); (10) 'Encontro de Lula e Trump cercado de tensão e desconfiança' (Estado de Minas 05/Mai); (11) Mantidos: 'Mendonça: Vorcaro tinha apoio mais altos escalões República'; 'Costa Neto antecipou acordo Flávio × Alcolumbre barrar CPI Master'; 'Tarcísio Flávio reportados PG'; 'STF Backlog 700 casos'; 'Caso Master: Ligação Gonet × Moraes obstáculo' (CNN 03/Mai); 'Lula aconselha Moraes Vorcaro' (MSN); Família Moraes processa A. Vieira PCC; PF apura Moraes imóveis luxo. POLYMARKET 05/Mai: Lula estável 36.50% × Flávio leve cede 44.05% (↓0.20pp), gap leve compressão +7.55pp Flávio. 2º lugar 62.50% (↓4.0pp DEVOLVE FORTE) × Lula 19.50% (estável). ZEMA DEVOLVE presidencial 4.65% (↓0.40pp). 3º LUGAR REORGANIZAÇÃO REVERSA: Zema 38% mantém liderança, Renan 36% RECUPERA (↑5pp), Caiado 16.5% DEVOLVE (↓2.5pp), Flávio 5.4% DEVOLVE (↓4.65pp), Eduardo Leite 3.0% DISPARA (↑2.15pp). Camilo 2L DISPARA 5.75% (↑1.90pp). Haddad 2L recupera 4.70% (↑1.05pp). Alckmin 2L DISPARA 2.20% (↑1.65pp). SENADO REORGANIZAÇÃO: PL 86.50% leve consolida, União 5.30% recupera, MDB 4.90% recupera forte, Republicanos 2.35% DISPARA, Podemos 1.25% DISPARA, PSB DEVOLVE 2.40%, PSD leve cede 5.40%. INFLAÇÃO: banda 5.00-5.49% consolida 38.40% (↑1.85pp), 6.00-6.49% DEVOLVE 16.95% (↓3.35pp), 7.00%+ DISPARA 11.80% (↑1.50pp). 'Real Time Big Data 1T Lula 40% × Flávio 34% sample 2.000 campo 02-04/Mai BR-03627/2026' (CNN Brasil 05/Mai). '2T Flávio 44% × Lula 43% empate' (R7 05/Mai). '2T Caiado 42% × Lula 43% empate' (Estadão 05/Mai). 'Tarcísio lança Alesp Senado crítica Haddad' (Folha 05/Mai 18:21). 'Flávio bate-volta EUA' (Poder360 05/Mai). 'Desaprovação Lula sobe 52%' (InfoMoney 05/Mai). 'Augusto Cury (Avante) 1%' (Real Time Big Data 05/Mai novo entrante 3ª via)."
    }
  }
}
